lsts/__init__.py
lsts/imputation.py
lsts/layers/AutoCorrelation.py
lsts/layers/Autoformer_EncDec.py
lsts/layers/Conv_Blocks.py
lsts/layers/Crossformer_EncDec.py
lsts/layers/ETSformer_EncDec.py
lsts/layers/Embed.py
lsts/layers/FourierCorrelation.py
lsts/layers/MultiWaveletCorrelation.py
lsts/layers/Pyraformer_EncDec.py
lsts/layers/SelfAttention_Family.py
lsts/layers/StandardNorm.py
lsts/layers/Transformer_EncDec.py
lsts/layers/__init__.py
lsts/long_term_forecast.py
lsts/models/DLinear.py
lsts/models/EALSTM.py
lsts/models/LSTM.py
lsts/models/PatchTST.py
lsts/models/TimesNet.py
lsts/models/__init__.py
lsts/models/iTransformer.py
lsts/requirements.txt
lsts/scaler/imputation_short_term_forecast_air_temperature.joblib
lsts/scaler/imputation_short_term_forecast_precipitation.joblib
lsts/scaler/imputation_short_term_forecast_snow_depth.joblib
lsts/scaler/imputation_short_term_forecast_snow_water_equivalent.joblib
lsts/scaler/imputation_short_term_forecast_soil_moisture.joblib
lsts/scaler/imputation_short_term_forecast_soil_suction.joblib
lsts/scaler/imputation_short_term_forecast_soil_temperature.joblib
lsts/scaler/imputation_short_term_forecast_surface_temperature.joblib
lsts/scaler/long_term_forecast_air_temperature.joblib
lsts/scaler/long_term_forecast_precipitation.joblib
lsts/scaler/long_term_forecast_snow_depth.joblib
lsts/scaler/long_term_forecast_snow_water_equivalent.joblib
lsts/scaler/long_term_forecast_soil_moisture.joblib
lsts/scaler/long_term_forecast_soil_suction.joblib
lsts/scaler/long_term_forecast_soil_temperature.joblib
lsts/scaler/long_term_forecast_surface_temperature.joblib
lsts/short_term_forecast.py
lsts/utils/__init__.py
lsts/utils/losses.py
lsts/utils/m4_summary.py
lsts/utils/masking.py
lsts/utils/metrics.py
lsts/utils/print_args.py
lsts/utils/timefeatures.py
lsts/utils/tools.py
lsts-0.2.1.dist-info/METADATA
lsts-0.2.1.dist-info/WHEEL
lsts-0.2.1.dist-info/RECORD
